{
  "tgt_word2id": {
    "": 11,
    "been": 23,
    "<s>": 1,
    "</s>": 2,
    "to": 5,
    "this": 16,
    "have": 8,
    "(Mock": 17,
    "<pad>": 0,
    "on": 19,
    "--": 9,
    "say": 20,
    "we": 28,
    "story": 24,
    "I": 4,
    "me.": 26,
    "And": 30,
    "what": 21,
    "of": 10,
    "<unk>": 3,
    "little": 27,
    "you": 13,
    "for": 14,
    "my": 25,
    "like": 18,
    "sob)": 29,
    "all": 22,
    "it": 31,
    "the": 7,
    "and": 15,
    "in": 12,
    "a": 6
  },
  "src_word2id": {
    "": 10,
    "<s>": 1,
    "en": 7,
    "</s>": 2,
    "para": 8,
    "de": 6,
    "<pad>": 0,
    "una": 13,
    "este": 16,
    "historia": 18,
    "fingidos)": 23,
    "un": 24,
    "<unk>": 3,
    "Nashville": 17,
    "parte": 20,
    "que": 5,
    "el": 25,
    "la": 14,
    "por": 12,
    "(Sollozos": 21,
    "y": 11,
    "lo": 15,
    "es": 19,
    "Y": 22,
    "--": 4,
    "a": 9
  }
}